YinzuoMamasangShuohuashu/README.md
YinzuoMamasangShuohuashu/__init__.py
YinzuoMamasangShuohuashu/__main__.py
YinzuoMamasangShuohuashu/file.pdf
YinzuoMamasangShuohuashu/index.html
yinzuo_mamasang_shuohuashu-2022.10.11.0.dist-info/METADATA
yinzuo_mamasang_shuohuashu-2022.10.11.0.dist-info/WHEEL
yinzuo_mamasang_shuohuashu-2022.10.11.0.dist-info/entry_points.txt
yinzuo_mamasang_shuohuashu-2022.10.11.0.dist-info/top_level.txt
yinzuo_mamasang_shuohuashu-2022.10.11.0.dist-info/RECORD
